translate_clix-1.0.0.dist-info/METADATA
translate_clix-1.0.0.dist-info/WHEEL
translate_clix-1.0.0.dist-info/entry_points.txt
translate_clix-1.0.0.dist-info/licenses/LICENSE.txt
translate_clix/__init__.py
translate_clix/lib/__init__.py
translate_clix/lib/api_handler/__init__.py
translate_clix/lib/api_handler/base_handler.py
translate_clix/lib/api_handler/v1_handler.py
translate_clix/lib/api_handler/v2_handler.py
translate_clix/lib/base.py
translate_clix/lib/constants.py
translate_clix/translate_clix.py
translate_clix-1.0.0.dist-info/RECORD
